LICENSE
MANIFEST.in
README
setup.py
colortuple/__init__.py
colortuple/colortuple.py
colortuple.egg-info/PKG-INFO
colortuple.egg-info/SOURCES.txt
colortuple.egg-info/dependency_links.txt
colortuple.egg-info/top_level.txt
colortuple.egg-info/zip-safe