Metadata-Version: 1.1
Name: colortuple
Version: 1.0.0
Summary: A namedtuple for storing RGBA color values, along with a few simple methods
Home-page: http://pypi.python.org/pypi/colortuple/
Author: Jonathan Hartley
Author-email: tartley@tartley.com
License: UNKNOWN
Keywords: color colour opengl OpenGL
Platform: UNKNOWN
Classifier: Development Status :: 5 - Production/Stable
Classifier: Intended Audience :: Developers
Classifier: License :: OSI Approved :: BSD License
Classifier: Natural Language :: English
Classifier: Operating System :: Microsoft :: Windows :: Windows 7
Classifier: Operating System :: MacOS :: MacOS X
Classifier: Operating System :: POSIX :: Linux
Classifier: Operating System :: OS Independent
Classifier: Programming Language :: Python :: 2
Classifier: Programming Language :: Python :: 2.7
Classifier: Programming Language :: Python :: 3
Classifier: Programming Language :: Python :: Implementation :: CPython
